orqa/__init__.py
orqa/_version.py
orqa/anomaly_detection.py
orqa/base.py
orqa/classification.py
orqa/cli.py
orqa/clustering.py
orqa/config.py
orqa/generative.py
orqa/integrate.py
orqa/main.py
orqa/regression.py
orqa_kit-0.1.0a1.dist-info/licenses/LICENSE
orqa_kit-0.1.0a1.dist-info/METADATA
orqa_kit-0.1.0a1.dist-info/WHEEL
orqa_kit-0.1.0a1.dist-info/entry_points.txt
orqa_kit-0.1.0a1.dist-info/top_level.txt
orqa_kit-0.1.0a1.dist-info/RECORD
