Metadata-Version: 2.4
Name: orqa-kit
Version: 0.1.0a1
Summary: ORQA — Open Research on Quantum Algorithms. A modular expert-ensemble framework (classical + quantum) with config-driven orchestration.
Author: Sai Pavan Velidandla
License: Polyform-Noncommercial-1.0.0
Keywords: machine-learning,ensemble,quantum,stacking,experts,orchestration
Classifier: Programming Language :: Python :: 3
Classifier: Programming Language :: Python :: 3 :: Only
Classifier: License :: Free for non-commercial use
Classifier: Operating System :: OS Independent
Classifier: Intended Audience :: Science/Research
Classifier: Topic :: Scientific/Engineering :: Artificial Intelligence
Requires-Python: >=3.9
License-File: LICENSE
Requires-Dist: numpy
Requires-Dist: pandas
Requires-Dist: scikit-learn
Requires-Dist: scipy
Requires-Dist: joblib
Provides-Extra: quantum
Requires-Dist: qiskit>=1.0; (platform_system != "Windows" or python_version >= "3.10") and extra == "quantum"
Dynamic: license-file
